oven/__init__.py
oven/__main__.py
oven/cli.py
oven/compiler.py
oven/language.py
oven/writer.py
oven_language-0.1.8.dist-info/licenses/LICENSE
oven_language-0.1.8.dist-info/METADATA
oven_language-0.1.8.dist-info/WHEEL
oven_language-0.1.8.dist-info/entry_points.txt
oven_language-0.1.8.dist-info/top_level.txt
oven_language-0.1.8.dist-info/RECORD
