Metadata-Version: 2.4
Name: oven-language
Version: 0.1.8
Summary: Python-to-MLIR compiler for GPU kernel development and mathematical computing
Author-email: Sinjin Jeong <sjjeong94@gmail.com>
License-Expression: MIT
Project-URL: Homepage, https://github.com/sjjeong94/oven-language
Project-URL: Repository, https://github.com/sjjeong94/oven-language
Project-URL: Issues, https://github.com/sjjeong94/oven-language/issues
Keywords: mlir,compiler,gpu,python,cuda,kernel,vectorization,mathematical-computing,llvm
Classifier: Development Status :: 4 - Beta
Classifier: Intended Audience :: Developers
Classifier: Intended Audience :: Science/Research
Classifier: Programming Language :: Python :: 3
Classifier: Programming Language :: Python :: 3.8
Classifier: Programming Language :: Python :: 3.9
Classifier: Programming Language :: Python :: 3.10
Classifier: Programming Language :: Python :: 3.11
Classifier: Programming Language :: Python :: 3.12
Classifier: Topic :: Software Development :: Compilers
Classifier: Topic :: Scientific/Engineering
Classifier: Topic :: System :: Hardware
Classifier: Topic :: Software Development :: Code Generators
Requires-Python: >=3.8
License-File: LICENSE
Provides-Extra: dev
Requires-Dist: pytest>=6.0; extra == "dev"
Requires-Dist: pytest-cov; extra == "dev"
Requires-Dist: black; extra == "dev"
Requires-Dist: flake8; extra == "dev"
Requires-Dist: mypy; extra == "dev"
Provides-Extra: test
Requires-Dist: pytest>=6.0; extra == "test"
Requires-Dist: pytest-cov; extra == "test"
Dynamic: license-file
